source_microsoft_onedrive/__init__.py
source_microsoft_onedrive/run.py
source_microsoft_onedrive/source.py
source_microsoft_onedrive/spec.py
source_microsoft_onedrive/stream_reader.py
airbyte_source_microsoft_onedrive-0.2.44.dist-info/METADATA
airbyte_source_microsoft_onedrive-0.2.44.dist-info/WHEEL
airbyte_source_microsoft_onedrive-0.2.44.dist-info/entry_points.txt
airbyte_source_microsoft_onedrive-0.2.44.dist-info/RECORD
