Metadata-Version: 2.3
Name: airbyte-source-microsoft-onedrive
Version: 0.2.44
Summary: Source implementation for Microsoft OneDrive.
License: MIT
Author: Airbyte
Author-email: contact@airbyte.io
Requires-Python: >=3.9,<3.12
Classifier: License :: OSI Approved :: MIT License
Classifier: Programming Language :: Python :: 3
Classifier: Programming Language :: Python :: 3.9
Classifier: Programming Language :: Python :: 3.10
Classifier: Programming Language :: Python :: 3.11
Requires-Dist: Office365-REST-Python-Client (==2.5.5)
Requires-Dist: airbyte-cdk[file-based] (>=1,<2)
Requires-Dist: msal (==1.25.0)
Requires-Dist: smart-open (==6.4.0)
Requires-Dist: transformers (==4.38.2)
Project-URL: Documentation, https://docs.airbyte.com/integrations/sources/microsoft-onedrive
Project-URL: Homepage, https://airbyte.com
Project-URL: Repository, https://github.com/airbytehq/airbyte
